pestcontrol/__init__.py
pestcontrol/pest_control.py
pestcontrol-1.0.5.dist-info/METADATA
pestcontrol-1.0.5.dist-info/RECORD
pestcontrol-1.0.5.dist-info/WHEEL
pestcontrol-1.0.5.dist-info/top_level.txt
