Metadata-Version: 2.1
Name: pestcontrol
Version: 1.0.5
Summary: A Python unit testing library
Home-page: https://gitlab.com/LukeBaal/PestControl
Author: Luke Baal
Author-email: lukebaal2020@gmail.com
License: UNKNOWN
Platform: UNKNOWN
Classifier: Programming Language :: Python :: 3
Classifier: License :: OSI Approved :: MIT License
Classifier: Operating System :: OS Independent
Requires-Dist: colorama
